confctl/__init__.py
confctl/__main__.py
confctl/cli.py
confctl-0.4.0.dist-info/entry_points.txt
confctl-0.4.0.dist-info/WHEEL
confctl-0.4.0.dist-info/METADATA
confctl-0.4.0.dist-info/RECORD
